sphinx_no_pragma.py
sphinx_no_pragma-0.1.2.dist-info/licenses/LICENSE
sphinx_no_pragma-0.1.2.dist-info/METADATA
sphinx_no_pragma-0.1.2.dist-info/WHEEL
sphinx_no_pragma-0.1.2.dist-info/top_level.txt
sphinx_no_pragma-0.1.2.dist-info/RECORD
