Metadata-Version: 2.4
Name: sphinx-no-pragma
Version: 0.1.2
Summary: Strip pragmas from your docs.
Author-email: Artur Barseghyan <artur.barseghyan@gmail.com>
License-Expression: MIT
Project-URL: Homepage, https://github.com/barseghyanartur/sphinx-no-pragma/
Project-URL: Bug Tracker, https://github.com/barseghyanartur/sphinx-no-pragma/issues
Project-URL: Documentation, https://sphinx-no-pragma.readthedocs.io/
Project-URL: Source Code, https://github.com/barseghyanartur/sphinx-no-pragma/
Project-URL: Changelog, https://sphinx-no-pragma.readthedocs.io/en/latest/changelog.html
Keywords: sphinx,documentation,pragma
Classifier: Development Status :: 4 - Beta
Classifier: Intended Audience :: Developers
Classifier: Operating System :: OS Independent
Classifier: Programming Language :: Python :: 3
Classifier: Programming Language :: Python :: 3.10
Classifier: Programming Language :: Python :: 3.11
Classifier: Programming Language :: Python :: 3.12
Classifier: Programming Language :: Python :: 3.13
Classifier: Programming Language :: Python :: 3.9
Classifier: Programming Language :: Python
Classifier: Topic :: Software Development :: Testing
Classifier: Topic :: Software Development
License-File: LICENSE
Requires-Dist: docutils
Requires-Dist: sphinx
Provides-Extra: all
Requires-Dist: sphinx-no-pragma[dev,docs,test]; extra == "all"
Provides-Extra: dev
Requires-Dist: black; extra == "dev"
Requires-Dist: detect-secrets; extra == "dev"
Requires-Dist: doc8; extra == "dev"
Requires-Dist: ipython; extra == "dev"
Requires-Dist: isort; extra == "dev"
Requires-Dist: mypy; extra == "dev"
Requires-Dist: ruff; extra == "dev"
Requires-Dist: twine; extra == "dev"
Requires-Dist: uv; extra == "dev"
Provides-Extra: test
Requires-Dist: pytest; extra == "test"
Requires-Dist: pytest-cov; extra == "test"
Requires-Dist: pytest-rst; extra == "test"
Provides-Extra: docs
Requires-Dist: sphinx-rtd-theme>=1.3.0; extra == "docs"
Dynamic: license-file
